{
	"configurations" : 
	[
		{
			"directories" : 
			[
				{
					"build" : ".",
					"hasInstallRule" : true,
					"jsonFile" : "directory-.-8786d96e649f1eab1d4c.json",
					"minimumCMakeVersion" : 
					{
						"string" : "3.12"
					},
					"projectIndex" : 0,
					"source" : ".",
					"targetIndexes" : 
					[
						0,
						1,
						2,
						3,
						4,
						5,
						6
					]
				}
			],
			"name" : "",
			"projects" : 
			[
				{
					"directoryIndexes" : 
					[
						0
					],
					"name" : "dynamixel_control",
					"targetIndexes" : 
					[
						0,
						1,
						2,
						3,
						4,
						5,
						6
					]
				}
			],
			"targets" : 
			[
				{
					"directoryIndex" : 0,
					"id" : "csv_joint_state_publisher::@6890427a1f51a3e7e1df",
					"jsonFile" : "target-csv_joint_state_publisher-31309f8a1c4fd0b7ade2.json",
					"name" : "csv_joint_state_publisher",
					"projectIndex" : 0
				},
				{
					"directoryIndex" : 0,
					"id" : "dynamixel_control_uninstall::@6890427a1f51a3e7e1df",
					"jsonFile" : "target-dynamixel_control_uninstall-bf4b1e45f2502d4c06fc.json",
					"name" : "dynamixel_control_uninstall",
					"projectIndex" : 0
				},
				{
					"directoryIndex" : 0,
					"id" : "joint_state_publisher::@6890427a1f51a3e7e1df",
					"jsonFile" : "target-joint_state_publisher-77bab625690e80bd17ff.json",
					"name" : "joint_state_publisher",
					"projectIndex" : 0
				},
				{
					"directoryIndex" : 0,
					"id" : "read_write_node::@6890427a1f51a3e7e1df",
					"jsonFile" : "target-read_write_node-ae051786fa5385b89d20.json",
					"name" : "read_write_node",
					"projectIndex" : 0
				},
				{
					"directoryIndex" : 0,
					"id" : "rviz_visualization_node::@6890427a1f51a3e7e1df",
					"jsonFile" : "target-rviz_visualization_node-402cd6d409e92aef3833.json",
					"name" : "rviz_visualization_node",
					"projectIndex" : 0
				},
				{
					"directoryIndex" : 0,
					"id" : "torque_compensation_node::@6890427a1f51a3e7e1df",
					"jsonFile" : "target-torque_compensation_node-99e575dcbf44e3af188e.json",
					"name" : "torque_compensation_node",
					"projectIndex" : 0
				},
				{
					"directoryIndex" : 0,
					"id" : "uninstall::@6890427a1f51a3e7e1df",
					"jsonFile" : "target-uninstall-6dc7be4befb57d58d56a.json",
					"name" : "uninstall",
					"projectIndex" : 0
				}
			]
		}
	],
	"kind" : "codemodel",
	"paths" : 
	{
		"build" : "/home/minwoong/OneDrive/JMW/dynamixel_8DOF/Dynamixel/build/dynamixel_control",
		"source" : "/home/minwoong/OneDrive/JMW/dynamixel_8DOF/Dynamixel/dynamixel_control"
	},
	"version" : 
	{
		"major" : 2,
		"minor" : 3
	}
}
